hyodo/__init__.py
hyodo/py.typed
hyodo-3.0.1.dist-info/METADATA
hyodo-3.0.1.dist-info/WHEEL
hyodo-3.0.1.dist-info/licenses/LICENSE
hyodo-3.0.1.dist-info/licenses/LICENSE.md
hyodo-3.0.1.dist-info/RECORD
