Metadata-Version: 2.4
Name: hyodo
Version: 3.0.1
Summary: AI Code Quality Automation - Claude Code Extension
Project-URL: Homepage, https://github.com/lofibrainwav/HyoDo
Project-URL: Documentation, https://github.com/lofibrainwav/HyoDo#readme
Project-URL: Repository, https://github.com/lofibrainwav/HyoDo
Project-URL: Issues, https://github.com/lofibrainwav/HyoDo/issues
Author-email: AFO Kingdom <afokingdom@example.com>
License-Expression: MIT
License-File: LICENSE
License-File: LICENSE.md
Keywords: ai,automation,claude,claude-code,code-quality,llm,trinity-score
Classifier: Development Status :: 4 - Beta
Classifier: Environment :: Console
Classifier: Intended Audience :: Developers
Classifier: License :: OSI Approved :: MIT License
Classifier: Operating System :: OS Independent
Classifier: Programming Language :: Python :: 3
Classifier: Programming Language :: Python :: 3.10
Classifier: Programming Language :: Python :: 3.11
Classifier: Programming Language :: Python :: 3.12
Classifier: Topic :: Software Development :: Quality Assurance
Classifier: Topic :: Software Development :: Testing
Requires-Python: >=3.10
Provides-Extra: dev
Requires-Dist: pytest-asyncio>=0.23; extra == 'dev'
Requires-Dist: pytest>=8.0; extra == 'dev'
Requires-Dist: ruff>=0.4; extra == 'dev'
